muselsl/__init__.py
muselsl/__main__.py
muselsl/backends.py
muselsl/cli.py
muselsl/constants.py
muselsl/helper.py
muselsl/muse.py
muselsl/record.py
muselsl/stream.py
muselsl/view.py
muselsl/viewer_v1.py
muselsl/viewer_v2.py
muselsl/docs/README.md
muselsl/docs/__init__.py
muselsl-2.3.1.dist-info/LICENSE.txt
muselsl-2.3.1.dist-info/METADATA
muselsl-2.3.1.dist-info/WHEEL
muselsl-2.3.1.dist-info/entry_points.txt
muselsl-2.3.1.dist-info/top_level.txt
muselsl-2.3.1.dist-info/RECORD
