Metadata-Version: 2.1
Name: muselsl
Version: 2.3.1
Summary: Stream and visualize EEG data from the Muse headset.
Home-page: https://github.com/alexandrebarachant/muse-lsl/
Author: Alexandre Barachant
Author-email: alexandre.barachant@gmail.com
License: BSD (3-clause)
Keywords: muse lsl eeg ble neuroscience
Classifier: Development Status :: 4 - Beta
Classifier: Intended Audience :: Science/Research
Classifier: Topic :: Software Development
Classifier: License :: OSI Approved :: BSD License
Classifier: Operating System :: Microsoft :: Windows
Classifier: Operating System :: POSIX
Classifier: Operating System :: Unix
Classifier: Operating System :: MacOS
Classifier: Programming Language :: Python
License-File: LICENSE.txt
Requires-Dist: bitstring
Requires-Dist: bleak>=0.18.0
Requires-Dist: pygatt
Requires-Dist: pandas
Requires-Dist: scikit-learn
Requires-Dist: numpy
Requires-Dist: seaborn
Requires-Dist: pexpect
Requires-Dist: pylsl
Provides-Extra: viewer-v2
Requires-Dist: mne; extra == "viewer-v2"
Requires-Dist: vispy; extra == "viewer-v2"
